pyggseqlogo/__init__.py
pyggseqlogo/logo.py
pyggseqlogo/theme.py
pyggseqlogo-1.2.0.dist-info/LICENSE
pyggseqlogo-1.2.0.dist-info/METADATA
pyggseqlogo-1.2.0.dist-info/WHEEL
pyggseqlogo-1.2.0.dist-info/top_level.txt
pyggseqlogo-1.2.0.dist-info/RECORD
