Metadata-Version: 2.2
Name: pyggseqlogo
Version: 1.2.0
Summary: Python version of ggseqlogo. Based on plotnine (Python version of ggplot2). A derivative of plotnineSeqSuite.
Home-page: https://github.com/caotianze/pyggseqlogo
Author: Cao Tianze
Author-email: hnrcao@qq.com
License: MIT
Project-URL: Bug Tracker, https://github.com/caotianze/pyggseqlogo/issues
Keywords: ggplot2,plotnine,ggseqlogo,Sequence logo
Classifier: Development Status :: 4 - Beta
Classifier: Programming Language :: Python :: 3
Classifier: Programming Language :: Python :: 3.11
Classifier: License :: OSI Approved :: MIT License
Classifier: Operating System :: OS Independent
Requires-Python: >=3.11
License-File: LICENSE
Requires-Dist: plotnineseqsuite>=1.2.0
Dynamic: author
Dynamic: author-email
Dynamic: classifier
Dynamic: description
Dynamic: description-content-type
Dynamic: home-page
Dynamic: keywords
Dynamic: license
Dynamic: project-url
Dynamic: requires-dist
Dynamic: requires-python
Dynamic: summary
